README.md
setup.py
testpy9875/__init__.py
testpy9875/t1.py
testpy9875.egg-info/PKG-INFO
testpy9875.egg-info/SOURCES.txt
testpy9875.egg-info/dependency_links.txt
testpy9875.egg-info/top_level.txt
testpy9875/core/__init__.py
testpy9875/core/main.py
testpy9875/core/person.py
testpy9875/core/student.py
testpy9875/utils/__init__.py
testpy9875/utils/print.py