Metadata-Version: 1.1
Name: testpy9875
Version: 1.2.0
Summary: 一个测试包而已，玩玩而已。
Home-page: http://blog.yoqi.me
Author: zztech
Author-email: zz1036@qq.com
License: UNKNOWN
Platform: UNKNOWN
Classifier: License :: OSI Approved :: MIT License
Classifier: Programming Language :: Python
Classifier: Intended Audience :: Developers
Classifier: Operating System :: OS Independent
